localtrust.py
summary.rst
extras/genpassword.py
trust/__init__.py
trust/exceptions.py
trust/file_finder.py
trust/trust.py
trust/trust_blueprint.py
trust/zipper.py
trust/audit/__init__.py
trust/audit/audit_to_log.py
trust/audit/audit_to_syslog.py
trust/audit/null_audit.py
trust/auth/__init__.py
trust/auth/in_data_auth_provider.py
trust/formatters/__init__.py
trust/formatters/complete_formatter.py
trust/formatters/json_formatter.py
trust/formatters/text_formatter.py
trust-1.0.19.dist-info/DESCRIPTION.rst
trust-1.0.19.dist-info/METADATA
trust-1.0.19.dist-info/RECORD
trust-1.0.19.dist-info/WHEEL
trust-1.0.19.dist-info/metadata.json
trust-1.0.19.dist-info/top_level.txt
