Metadata-Version: 2.0
Name: trust
Version: 1.0.19
Summary: A hierarchical database engine with read-only access to data, ideally used for cross-application settings and infrastructure description.
Home-page: https://go.pelicandd.com/n/python-trust
Author: Arseni Mourzenko
Author-email: arseni.mourzenko@pelicandd.com
License: MIT
Keywords: database json settings
Platform: UNKNOWN
Requires-Dist: flask (==2.1.2)
Requires-Dist: passlib (==1.7.4)
